{
    "/assets/admin/default/admin.js": "/assets/admin/default/admin.js",
    "/assets/admin/default/admin.css": "/assets/admin/default/admin.css",
    "/assets/admin/default/icons.css": "/assets/admin/default/icons.css",
    "/assets/auth/default/auth.css": "/assets/auth/default/auth.css",
    "/assets/errors/default/errors.css": "/assets/errors/default/errors.css",
    "/assets/uploader/default/uploader.css": "/assets/uploader/default/uploader.css",
    "/assets/admin/default/boxes.js": "/assets/admin/default/boxes.js",
    "/assets/admin/default/icons.js": "/assets/admin/default/icons.js",
    "/assets/admin/default/store.js": "/assets/admin/default/store.js",
    "/assets/uploader/default/uploader.js": "/assets/uploader/default/uploader.js",
    "/assets/uploader/default/uploader2.js": "/assets/uploader/default/uploader2.js"
}
